vivlio/Alert Settings/CSV/.gitignore
vivlio/Alert Settings/HTML/.gitignore
vivlio/Alert Settings/JSON/.gitignore
vivlio/Alert Settings/Markdown/.gitignore
vivlio/Alert Settings/Mindmap/.gitignore
vivlio/Alert Settings/YAML/.gitignore
vivlio/Clients/CSV/.gitignore
vivlio/Clients/HTML/.gitignore
vivlio/Clients/JSON/.gitignore
vivlio/Clients/Markdown/.gitignore
vivlio/Clients/Mindmap/.gitignore
vivlio/Clients/YAML/.gitignore
vivlio/Devices/CSV/.gitignore
vivlio/Devices/HTML/.gitignore
vivlio/Devices/JSON/.gitignore
vivlio/Devices/Markdown/.gitignore
vivlio/Devices/Mindmap/.gitignore
vivlio/Devices/YAML/.gitignore
vivlio/Management Interfaces/CSV/.gitignore
vivlio/Management Interfaces/HTML/.gitignore
vivlio/Management Interfaces/JSON/.gitignore
vivlio/Management Interfaces/Markdown/.gitignore
vivlio/Management Interfaces/Mindmap/.gitignore
vivlio/Management Interfaces/YAML/.gitignore
vivlio/Networks/CSV/.gitignore
vivlio/Networks/HTML/.gitignore
vivlio/Networks/JSON/.gitignore
vivlio/Networks/Markdown/.gitignore
vivlio/Networks/Mindmap/.gitignore
vivlio/Networks/YAML/.gitignore
vivlio/Organizations/CSV/.gitignore
vivlio/Organizations/HTML/.gitignore
vivlio/Organizations/JSON/.gitignore
vivlio/Organizations/Markdown/.gitignore
vivlio/Organizations/Mindmap/.gitignore
vivlio/Organizations/YAML/.gitignore
vivlio/__init__.py
vivlio/datatable_footer.j2
vivlio/datatable_header.j2
vivlio/script.py
vivlio/vivlio.py
vivlio/vivlio_csv.j2
vivlio/vivlio_html.j2
vivlio/vivlio_markdown.j2
vivlio/vivlio_mindmap.j2
vivlio-1.0.2.dist-info/METADATA
vivlio-1.0.2.dist-info/WHEEL
vivlio-1.0.2.dist-info/LICENSE
vivlio-1.0.2.dist-info/entry_points.txt
vivlio-1.0.2.dist-info/RECORD
